realerikrani/base64token/__init__.py
realerikrani/base64token/py.typed
realerikrani/base64token/token.py
realerikrani_base64token-1.0.1.dist-info/LICENSE
realerikrani_base64token-1.0.1.dist-info/METADATA
realerikrani_base64token-1.0.1.dist-info/WHEEL
realerikrani_base64token-1.0.1.dist-info/top_level.txt
realerikrani_base64token-1.0.1.dist-info/RECORD
