Metadata-Version: 2.1
Name: realerikrani-base64token
Version: 1.0.1
Summary: Encode list of tuples into a string. Decode that string into a dictionary.
License: Apache-2.0
Project-URL: Repository, https://github.com/realerikrani/base64token
Requires-Python: >=3.10
License-File: LICENSE
